[
  {
    "ContainingType": "ProjectAPI.Controllers.AccountController",
    "Method": "DeleteUser",
    "RelativePath": "api/Account",
    "HttpMethod": "DELETE",
    "IsController": true,
    "Order": 0,
    "Parameters": [],
    "ReturnTypes": []
  },
  {
    "ContainingType": "ProjectAPI.Controllers.AccountController",
    "Method": "UpdateUser",
    "RelativePath": "api/Account/EditUser",
    "HttpMethod": "PUT",
    "IsController": true,
    "Order": 0,
    "Parameters": [
      {
        "Name": "Photo",
        "Type": "Microsoft.AspNetCore.Http.IFormFile",
        "IsRequired": false
      },
      {
        "Name": "FirstName",
        "Type": "System.String",
        "IsRequired": false
      },
      {
        "Name": "LastName",
        "Type": "System.String",
        "IsRequired": false
      },
      {
        "Name": "Email",
        "Type": "System.String",
        "IsRequired": false
      },
      {
        "Name": "PhoneNamber",
        "Type": "System.String",
        "IsRequired": false
      },
      {
        "Name": "Address",
        "Type": "System.String",
        "IsRequired": false
      },
      {
        "Name": "BirthDay",
        "Type": "System.String",
        "IsRequired": false
      },
      {
        "Name": "Location",
        "Type": "System.String",
        "IsRequired": false
      }
    ],
    "ReturnTypes": []
  },
  {
    "ContainingType": "ProjectAPI.Controllers.AccountController",
    "Method": "GetUser",
    "RelativePath": "api/Account/GetUser",
    "HttpMethod": "GET",
    "IsController": true,
    "Order": 0,
    "Parameters": [],
    "ReturnTypes": []
  },
  {
    "ContainingType": "ProjectAPI.Controllers.AccountController",
    "Method": "GetUsers",
    "RelativePath": "api/Account/GetUsers",
    "HttpMethod": "GET",
    "IsController": true,
    "Order": 0,
    "Parameters": [],
    "ReturnTypes": []
  },
  {
    "ContainingType": "ProjectAPI.Controllers.AuthenticateController",
    "Method": "ChangePassword",
    "RelativePath": "api/Authenticate/ChangePassword/{id}",
    "HttpMethod": "POST",
    "IsController": true,
    "Order": 0,
    "Parameters": [
      {
        "Name": "NewPassword",
        "Type": "System.String",
        "IsRequired": false
      },
      {
        "Name": "ConfirmedNewPassword",
        "Type": "System.String",
        "IsRequired": false
      },
      {
        "Name": "id",
        "Type": "System.String",
        "IsRequired": true
      }
    ],
    "ReturnTypes": []
  },
  {
    "ContainingType": "ProjectAPI.Controllers.AuthenticateController",
    "Method": "ForgetPassword",
    "RelativePath": "api/Authenticate/ForgetPassword",
    "HttpMethod": "POST",
    "IsController": true,
    "Order": 0,
    "Parameters": [
      {
        "Name": "dto",
        "Type": "Core.AuthenticationDTO.ForgetPasswordDTO",
        "IsRequired": true
      }
    ],
    "ReturnTypes": []
  },
  {
    "ContainingType": "ProjectAPI.Controllers.AuthenticateController",
    "Method": "Login",
    "RelativePath": "api/Authenticate/Login",
    "HttpMethod": "POST",
    "IsController": true,
    "Order": 0,
    "Parameters": [
      {
        "Name": "dto",
        "Type": "Core.AuthenticationDTO.LogInDTo",
        "IsRequired": true
      }
    ],
    "ReturnTypes": []
  },
  {
    "ContainingType": "ProjectAPI.Controllers.AuthenticateController",
    "Method": "RefreshToken",
    "RelativePath": "api/Authenticate/RefreshToken",
    "HttpMethod": "GET",
    "IsController": true,
    "Order": 0,
    "Parameters": [],
    "ReturnTypes": []
  },
  {
    "ContainingType": "ProjectAPI.Controllers.AuthenticateController",
    "Method": "Register",
    "RelativePath": "api/Authenticate/Register",
    "HttpMethod": "POST",
    "IsController": true,
    "Order": 0,
    "Parameters": [
      {
        "Name": "dto",
        "Type": "Core.AuthenticationDTO.RegisterDTO",
        "IsRequired": true
      }
    ],
    "ReturnTypes": []
  },
  {
    "ContainingType": "ProjectAPI.Controllers.AuthenticateController",
    "Method": "RevokeToken",
    "RelativePath": "api/Authenticate/RevokeToken",
    "HttpMethod": "POST",
    "IsController": true,
    "Order": 0,
    "Parameters": [
      {
        "Name": "dto",
        "Type": "Core.AuthenticationDTO.RevokeTokenDTO",
        "IsRequired": true
      }
    ],
    "ReturnTypes": []
  },
  {
    "ContainingType": "ProjectAPI.Controllers.FeedbackController",
    "Method": "AddMessage",
    "RelativePath": "api/Feedback/AddMessage",
    "HttpMethod": "POST",
    "IsController": true,
    "Order": 0,
    "Parameters": [
      {
        "Name": "dto",
        "Type": "ProjectAPI.DTO.AddMessageDTO",
        "IsRequired": true
      }
    ],
    "ReturnTypes": []
  },
  {
    "ContainingType": "ProjectAPI.Controllers.FeedbackController",
    "Method": "DeleteMessage",
    "RelativePath": "api/Feedback/DeleteMessage/{feedBackId}",
    "HttpMethod": "DELETE",
    "IsController": true,
    "Order": 0,
    "Parameters": [
      {
        "Name": "feedBackId",
        "Type": "System.String",
        "IsRequired": true
      }
    ],
    "ReturnTypes": []
  },
  {
    "ContainingType": "ProjectAPI.Controllers.FeedbackController",
    "Method": "FeedBack",
    "RelativePath": "api/Feedback/GetFeedBack",
    "HttpMethod": "GET",
    "IsController": true,
    "Order": 0,
    "Parameters": [],
    "ReturnTypes": []
  },
  {
    "ContainingType": "ProjectAPI.Controllers.FeedbackController",
    "Method": "UpdateMessage",
    "RelativePath": "api/Feedback/UpdateMessage/{feedBackId}",
    "HttpMethod": "PUT",
    "IsController": true,
    "Order": 0,
    "Parameters": [
      {
        "Name": "feedBackId",
        "Type": "System.String",
        "IsRequired": true
      },
      {
        "Name": "dto",
        "Type": "ProjectAPI.DTO.UpdateMessageDTO",
        "IsRequired": true
      }
    ],
    "ReturnTypes": []
  },
  {
    "ContainingType": "ProjectAPI.Controllers.FrameworksController",
    "Method": "AddFramework",
    "RelativePath": "api/Frameworks/AddFramework",
    "HttpMethod": "POST",
    "IsController": true,
    "Order": 0,
    "Parameters": [
      {
        "Name": "MainTrackId",
        "Type": "System.String",
        "IsRequired": false
      },
      {
        "Name": "FramworkName",
        "Type": "System.String",
        "IsRequired": false
      },
      {
        "Name": "Photo",
        "Type": "Microsoft.AspNetCore.Http.IFormFile",
        "IsRequired": false
      },
      {
        "Name": "description",
        "Type": "System.String",
        "IsRequired": false
      }
    ],
    "ReturnTypes": []
  },
  {
    "ContainingType": "ProjectAPI.Controllers.FrameworksController",
    "Method": "DeleteFramework",
    "RelativePath": "api/Frameworks/DeleteFramework/{frameworkId}",
    "HttpMethod": "DELETE",
    "IsController": true,
    "Order": 0,
    "Parameters": [
      {
        "Name": "frameworkId",
        "Type": "System.String",
        "IsRequired": true
      }
    ],
    "ReturnTypes": []
  },
  {
    "ContainingType": "ProjectAPI.Controllers.FrameworksController",
    "Method": "GetFramework",
    "RelativePath": "api/Frameworks/GetFramework/{mainTrackId}",
    "HttpMethod": "GET",
    "IsController": true,
    "Order": 0,
    "Parameters": [
      {
        "Name": "mainTrackId",
        "Type": "System.String",
        "IsRequired": true
      }
    ],
    "ReturnTypes": []
  },
  {
    "ContainingType": "ProjectAPI.Controllers.FrameworksController",
    "Method": "UpdateFramewrok",
    "RelativePath": "api/Frameworks/UpdateFramewrok/{frameworkId}",
    "HttpMethod": "PUT",
    "IsController": true,
    "Order": 0,
    "Parameters": [
      {
        "Name": "frameworkId",
        "Type": "System.String",
        "IsRequired": true
      },
      {
        "Name": "FrameworkName",
        "Type": "System.String",
        "IsRequired": false
      },
      {
        "Name": "Photo",
        "Type": "Microsoft.AspNetCore.Http.IFormFile",
        "IsRequired": false
      },
      {
        "Name": "description",
        "Type": "System.String",
        "IsRequired": false
      }
    ],
    "ReturnTypes": []
  },
  {
    "ContainingType": "ProjectAPI.Controllers.GroupsController",
    "Method": "CreateGroup",
    "RelativePath": "api/Groups/CreateGroup",
    "HttpMethod": "POST",
    "IsController": true,
    "Order": 0,
    "Parameters": [
      {
        "Name": "GroupName",
        "Type": "System.String",
        "IsRequired": false
      },
      {
        "Name": "Photo",
        "Type": "Microsoft.AspNetCore.Http.IFormFile",
        "IsRequired": false
      },
      {
        "Name": "Description",
        "Type": "System.String",
        "IsRequired": false
      }
    ],
    "ReturnTypes": []
  },
  {
    "ContainingType": "ProjectAPI.Controllers.GroupsController",
    "Method": "DeleteGroup",
    "RelativePath": "api/Groups/DeleteGroup/{id}",
    "HttpMethod": "DELETE",
    "IsController": true,
    "Order": 0,
    "Parameters": [
      {
        "Name": "id",
        "Type": "System.String",
        "IsRequired": true
      }
    ],
    "ReturnTypes": []
  },
  {
    "ContainingType": "ProjectAPI.Controllers.GroupsController",
    "Method": "GetAllGroups",
    "RelativePath": "api/Groups/GetAllGroups",
    "HttpMethod": "GET",
    "IsController": true,
    "Order": 0,
    "Parameters": [],
    "ReturnTypes": []
  },
  {
    "ContainingType": "ProjectAPI.Controllers.GroupsController",
    "Method": "GetGroupById",
    "RelativePath": "api/Groups/GetGroupById/{id}",
    "HttpMethod": "GET",
    "IsController": true,
    "Order": 0,
    "Parameters": [
      {
        "Name": "id",
        "Type": "System.String",
        "IsRequired": true
      }
    ],
    "ReturnTypes": []
  },
  {
    "ContainingType": "ProjectAPI.Controllers.GroupsController",
    "Method": "UpdateGroup",
    "RelativePath": "api/Groups/UpdateGroup/{id}",
    "HttpMethod": "PUT",
    "IsController": true,
    "Order": 0,
    "Parameters": [
      {
        "Name": "id",
        "Type": "System.String",
        "IsRequired": true
      },
      {
        "Name": "GroupName",
        "Type": "System.String",
        "IsRequired": false
      },
      {
        "Name": "Photo",
        "Type": "Microsoft.AspNetCore.Http.IFormFile",
        "IsRequired": false
      },
      {
        "Name": "Description",
        "Type": "System.String",
        "IsRequired": false
      }
    ],
    "ReturnTypes": []
  },
  {
    "ContainingType": "ProjectAPI.Controllers.LikesController",
    "Method": "AddLike",
    "RelativePath": "api/Likes/AddLike/{postId}",
    "HttpMethod": "POST",
    "IsController": true,
    "Order": 0,
    "Parameters": [
      {
        "Name": "postId",
        "Type": "System.String",
        "IsRequired": true
      }
    ],
    "ReturnTypes": []
  },
  {
    "ContainingType": "ProjectAPI.Controllers.LikesController",
    "Method": "RemoveLike",
    "RelativePath": "api/Likes/RemoveLike/{postId}",
    "HttpMethod": "POST",
    "IsController": true,
    "Order": 0,
    "Parameters": [
      {
        "Name": "postId",
        "Type": "System.String",
        "IsRequired": true
      }
    ],
    "ReturnTypes": []
  },
  {
    "ContainingType": "ProjectAPI.Controllers.MainTrackController",
    "Method": "AddMainTrack",
    "RelativePath": "api/MainTrack/AddMainTrack",
    "HttpMethod": "POST",
    "IsController": true,
    "Order": 0,
    "Parameters": [
      {
        "Name": "TarckName",
        "Type": "System.String",
        "IsRequired": false
      },
      {
        "Name": "Photo",
        "Type": "Microsoft.AspNetCore.Http.IFormFile",
        "IsRequired": false
      },
      {
        "Name": "description",
        "Type": "System.String",
        "IsRequired": false
      }
    ],
    "ReturnTypes": []
  },
  {
    "ContainingType": "ProjectAPI.Controllers.MainTrackController",
    "Method": "DeleteTrack",
    "RelativePath": "api/MainTrack/DeleteTrack/{trackID}",
    "HttpMethod": "DELETE",
    "IsController": true,
    "Order": 0,
    "Parameters": [
      {
        "Name": "trackID",
        "Type": "System.String",
        "IsRequired": true
      }
    ],
    "ReturnTypes": []
  },
  {
    "ContainingType": "ProjectAPI.Controllers.MainTrackController",
    "Method": "GetMainTrack",
    "RelativePath": "api/MainTrack/GetMainTrack",
    "HttpMethod": "GET",
    "IsController": true,
    "Order": 0,
    "Parameters": [],
    "ReturnTypes": []
  },
  {
    "ContainingType": "ProjectAPI.Controllers.MainTrackController",
    "Method": "UpdateMaintrack",
    "RelativePath": "api/MainTrack/UpdateMaintrack/{TrackId}",
    "HttpMethod": "PUT",
    "IsController": true,
    "Order": 0,
    "Parameters": [
      {
        "Name": "TarckName",
        "Type": "System.String",
        "IsRequired": false
      },
      {
        "Name": "Photo",
        "Type": "Microsoft.AspNetCore.Http.IFormFile",
        "IsRequired": false
      },
      {
        "Name": "description",
        "Type": "System.String",
        "IsRequired": false
      },
      {
        "Name": "TrackId",
        "Type": "System.String",
        "IsRequired": true
      }
    ],
    "ReturnTypes": []
  },
  {
    "ContainingType": "ProjectAPI.Controllers.PostsController",
    "Method": "CreatePost",
    "RelativePath": "api/Posts/CreatePost",
    "HttpMethod": "POST",
    "IsController": true,
    "Order": 0,
    "Parameters": [
      {
        "Name": "header",
        "Type": "System.String",
        "IsRequired": false
      },
      {
        "Name": "TypeOfBody",
        "Type": "System.String",
        "IsRequired": false
      },
      {
        "Name": "groupId",
        "Type": "System.String",
        "IsRequired": false
      },
      {
        "Name": "Text",
        "Type": "System.String",
        "IsRequired": false
      },
      {
        "Name": "Images",
        "Type": "System.Collections.Generic.List\u00601[[Microsoft.AspNetCore.Http.IFormFile, Microsoft.AspNetCore.Http.Features, Version=8.0.0.0, Culture=neutral, PublicKeyToken=adb9793829ddae60]]",
        "IsRequired": false
      }
    ],
    "ReturnTypes": []
  },
  {
    "ContainingType": "ProjectAPI.Controllers.PostsController",
    "Method": "DeletePost",
    "RelativePath": "api/Posts/DeletePost/{PostId}",
    "HttpMethod": "DELETE",
    "IsController": true,
    "Order": 0,
    "Parameters": [
      {
        "Name": "PostId",
        "Type": "System.String",
        "IsRequired": true
      }
    ],
    "ReturnTypes": []
  },
  {
    "ContainingType": "ProjectAPI.Controllers.PostsController",
    "Method": "GetAllPosts",
    "RelativePath": "api/Posts/GetAllPosts/{groupId}",
    "HttpMethod": "GET",
    "IsController": true,
    "Order": 0,
    "Parameters": [
      {
        "Name": "groupId",
        "Type": "System.String",
        "IsRequired": true
      }
    ],
    "ReturnTypes": []
  },
  {
    "ContainingType": "ProjectAPI.Controllers.PostsController",
    "Method": "UpdatePost",
    "RelativePath": "api/Posts/UpdatePost/{PostId}",
    "HttpMethod": "PUT",
    "IsController": true,
    "Order": 0,
    "Parameters": [
      {
        "Name": "header",
        "Type": "System.String",
        "IsRequired": false
      },
      {
        "Name": "Text",
        "Type": "System.String",
        "IsRequired": false
      },
      {
        "Name": "Images",
        "Type": "System.Collections.Generic.List\u00601[[Microsoft.AspNetCore.Http.IFormFile, Microsoft.AspNetCore.Http.Features, Version=8.0.0.0, Culture=neutral, PublicKeyToken=adb9793829ddae60]]",
        "IsRequired": false
      },
      {
        "Name": "PostId",
        "Type": "System.String",
        "IsRequired": true
      }
    ],
    "ReturnTypes": []
  },
  {
    "ContainingType": "ProjectAPI.Controllers.QuestionsController",
    "Method": "AddQuestionFromRequest",
    "RelativePath": "api/Questions/AddQuestion/{level}/{requestQuestionId}",
    "HttpMethod": "POST",
    "IsController": true,
    "Order": 0,
    "Parameters": [
      {
        "Name": "requestQuestionId",
        "Type": "System.String",
        "IsRequired": true
      },
      {
        "Name": "level",
        "Type": "System.String",
        "IsRequired": true
      }
    ],
    "ReturnTypes": []
  },
  {
    "ContainingType": "ProjectAPI.Controllers.QuestionsController",
    "Method": "AddQuestionFromAdmin",
    "RelativePath": "api/Questions/AddQuestionFromAdmin/{level}",
    "HttpMethod": "POST",
    "IsController": true,
    "Order": 0,
    "Parameters": [
      {
        "Name": "dto",
        "Type": "ProjectAPI.DTO.AddQuestionsDTO",
        "IsRequired": true
      },
      {
        "Name": "level",
        "Type": "System.String",
        "IsRequired": true
      }
    ],
    "ReturnTypes": []
  },
  {
    "ContainingType": "ProjectAPI.Controllers.QuestionsController",
    "Method": "DeleteQuestion",
    "RelativePath": "api/Questions/DeleteQuestion/{questionId}",
    "HttpMethod": "DELETE",
    "IsController": true,
    "Order": 0,
    "Parameters": [
      {
        "Name": "questionId",
        "Type": "System.String",
        "IsRequired": true
      }
    ],
    "ReturnTypes": []
  },
  {
    "ContainingType": "ProjectAPI.Controllers.QuestionsController",
    "Method": "Q_Advanced",
    "RelativePath": "api/Questions/Q_AdvancedLevel/{frameworkId}",
    "HttpMethod": "GET",
    "IsController": true,
    "Order": 0,
    "Parameters": [
      {
        "Name": "frameworkId",
        "Type": "System.String",
        "IsRequired": true
      }
    ],
    "ReturnTypes": []
  },
  {
    "ContainingType": "ProjectAPI.Controllers.QuestionsController",
    "Method": "Q_beginner",
    "RelativePath": "api/Questions/Q_BeginnerLevel/{frameworkId}",
    "HttpMethod": "GET",
    "IsController": true,
    "Order": 0,
    "Parameters": [
      {
        "Name": "frameworkId",
        "Type": "System.String",
        "IsRequired": true
      }
    ],
    "ReturnTypes": []
  },
  {
    "ContainingType": "ProjectAPI.Controllers.QuestionsController",
    "Method": "Q_Intermediate",
    "RelativePath": "api/Questions/Q_IntermediateLevel/{frameworkId}",
    "HttpMethod": "GET",
    "IsController": true,
    "Order": 0,
    "Parameters": [
      {
        "Name": "frameworkId",
        "Type": "System.String",
        "IsRequired": true
      }
    ],
    "ReturnTypes": []
  },
  {
    "ContainingType": "ProjectAPI.Controllers.QuestionsController",
    "Method": "UpdateQuestion",
    "RelativePath": "api/Questions/UpdateQuestion/{questionId}",
    "HttpMethod": "PUT",
    "IsController": true,
    "Order": 0,
    "Parameters": [
      {
        "Name": "dto",
        "Type": "ProjectAPI.DTO.UpdateQuestionDTO",
        "IsRequired": true
      },
      {
        "Name": "questionId",
        "Type": "System.String",
        "IsRequired": true
      }
    ],
    "ReturnTypes": []
  },
  {
    "ContainingType": "ProjectAPI.Controllers.RecentController",
    "Method": "AddInRecentTable",
    "RelativePath": "api/Recent/AddInRecentTable/{mainTrackId}",
    "HttpMethod": "POST",
    "IsController": true,
    "Order": 0,
    "Parameters": [
      {
        "Name": "mainTrackId",
        "Type": "System.String",
        "IsRequired": true
      }
    ],
    "ReturnTypes": []
  },
  {
    "ContainingType": "ProjectAPI.Controllers.RecentController",
    "Method": "GetRecently",
    "RelativePath": "api/Recent/GetRecently",
    "HttpMethod": "GET",
    "IsController": true,
    "Order": 0,
    "Parameters": [],
    "ReturnTypes": []
  },
  {
    "ContainingType": "ProjectAPI.Controllers.RequestController",
    "Method": "AddQuestionRequest",
    "RelativePath": "api/Request/AddQuestionRequest",
    "HttpMethod": "POST",
    "IsController": true,
    "Order": 0,
    "Parameters": [
      {
        "Name": "dto",
        "Type": "ProjectAPI.DTO.AddQuestionsDTO",
        "IsRequired": true
      }
    ],
    "ReturnTypes": []
  },
  {
    "ContainingType": "ProjectAPI.Controllers.RequestController",
    "Method": "DeleteRequest",
    "RelativePath": "api/Request/DeleteRequest/{requestId}",
    "HttpMethod": "DELETE",
    "IsController": true,
    "Order": 0,
    "Parameters": [
      {
        "Name": "requestId",
        "Type": "System.String",
        "IsRequired": true
      }
    ],
    "ReturnTypes": []
  },
  {
    "ContainingType": "ProjectAPI.Controllers.RequestController",
    "Method": "GetRequests",
    "RelativePath": "api/Request/GetRequests",
    "HttpMethod": "GET",
    "IsController": true,
    "Order": 0,
    "Parameters": [],
    "ReturnTypes": []
  },
  {
    "ContainingType": "ProjectAPI.Controllers.RequestController",
    "Method": "UpdateRequest",
    "RelativePath": "api/Request/UpdateRequest/{requestId}",
    "HttpMethod": "POST",
    "IsController": true,
    "Order": 0,
    "Parameters": [
      {
        "Name": "dto",
        "Type": "ProjectAPI.DTO.UpdateRequestDTO",
        "IsRequired": true
      },
      {
        "Name": "requestId",
        "Type": "System.String",
        "IsRequired": true
      }
    ],
    "ReturnTypes": []
  },
  {
    "ContainingType": "ProjectAPI.Controllers.RolesController",
    "Method": "AddRole",
    "RelativePath": "api/Roles/AddRole",
    "HttpMethod": "POST",
    "IsController": true,
    "Order": 0,
    "Parameters": [
      {
        "Name": "dto",
        "Type": "Core.AuthenticationDTO.RoleDTO",
        "IsRequired": true
      }
    ],
    "ReturnTypes": []
  },
  {
    "ContainingType": "ProjectAPI.Controllers.RolesController",
    "Method": "AddRolesToUser",
    "RelativePath": "api/Roles/AddRolesToUser",
    "HttpMethod": "POST",
    "IsController": true,
    "Order": 0,
    "Parameters": [
      {
        "Name": "UserId",
        "Type": "System.String",
        "IsRequired": false
      },
      {
        "Name": "RoleName",
        "Type": "System.String",
        "IsRequired": false
      }
    ],
    "ReturnTypes": []
  },
  {
    "ContainingType": "ProjectAPI.Controllers.RolesController",
    "Method": "DeleteRole",
    "RelativePath": "api/Roles/DeleteRole/{RoleId}",
    "HttpMethod": "DELETE",
    "IsController": true,
    "Order": 0,
    "Parameters": [
      {
        "Name": "roleId",
        "Type": "System.String",
        "IsRequired": true
      }
    ],
    "ReturnTypes": []
  },
  {
    "ContainingType": "ProjectAPI.Controllers.RolesController",
    "Method": "DeleteRoleFromUser",
    "RelativePath": "api/Roles/DeleteRoleFromUser/{RoleId}/{userId}",
    "HttpMethod": "DELETE",
    "IsController": true,
    "Order": 0,
    "Parameters": [
      {
        "Name": "roleId",
        "Type": "System.String",
        "IsRequired": true
      },
      {
        "Name": "userId",
        "Type": "System.String",
        "IsRequired": true
      }
    ],
    "ReturnTypes": []
  },
  {
    "ContainingType": "ProjectAPI.Controllers.RolesController",
    "Method": "GetRols",
    "RelativePath": "api/Roles/GetRoles",
    "HttpMethod": "GET",
    "IsController": true,
    "Order": 0,
    "Parameters": [],
    "ReturnTypes": []
  },
  {
    "ContainingType": "ProjectAPI.Controllers.RolesController",
    "Method": "GetUserRoles",
    "RelativePath": "api/Roles/GetUserRoles",
    "HttpMethod": "GET",
    "IsController": true,
    "Order": 0,
    "Parameters": [],
    "ReturnTypes": []
  },
  {
    "ContainingType": "ProjectAPI.Controllers.RolesController",
    "Method": "GetUserRolesfromAdmin",
    "RelativePath": "api/Roles/GetUserRolesfromAdmin/{userId}",
    "HttpMethod": "GET",
    "IsController": true,
    "Order": 0,
    "Parameters": [
      {
        "Name": "userId",
        "Type": "System.String",
        "IsRequired": true
      }
    ],
    "ReturnTypes": []
  },
  {
    "ContainingType": "ProjectAPI.Controllers.RolesController",
    "Method": "UpdateRole",
    "RelativePath": "api/Roles/UpdateRole/{roleId}",
    "HttpMethod": "PUT",
    "IsController": true,
    "Order": 0,
    "Parameters": [
      {
        "Name": "roleId",
        "Type": "System.String",
        "IsRequired": true
      },
      {
        "Name": "dto",
        "Type": "Core.AuthenticationDTO.RoleDTO",
        "IsRequired": true
      }
    ],
    "ReturnTypes": []
  },
  {
    "ContainingType": "ProjectAPI.Controllers.RolesController",
    "Method": "UpdateRoleToUser",
    "RelativePath": "api/Roles/UpdateRoleToUser/{roleId}",
    "HttpMethod": "PUT",
    "IsController": true,
    "Order": 0,
    "Parameters": [
      {
        "Name": "roleId",
        "Type": "System.String",
        "IsRequired": true
      },
      {
        "Name": "dto",
        "Type": "Core.AuthenticationDTO.RoleToUserDTO",
        "IsRequired": true
      }
    ],
    "ReturnTypes": []
  },
  {
    "ContainingType": "ProjectAPI.Controllers.SaveController",
    "Method": "AddIntoSave",
    "RelativePath": "api/Save/AddtoSave",
    "HttpMethod": "POST",
    "IsController": true,
    "Order": 0,
    "Parameters": [
      {
        "Name": "dto",
        "Type": "ProjectAPI.DTO.AddIntoSaveDTO",
        "IsRequired": true
      }
    ],
    "ReturnTypes": []
  },
  {
    "ContainingType": "ProjectAPI.Controllers.SaveController",
    "Method": "DeleteFromSave",
    "RelativePath": "api/Save/DeleteFromSave",
    "HttpMethod": "DELETE",
    "IsController": true,
    "Order": 0,
    "Parameters": [
      {
        "Name": "Id",
        "Type": "System.String",
        "IsRequired": false
      }
    ],
    "ReturnTypes": []
  },
  {
    "ContainingType": "ProjectAPI.Controllers.SaveController",
    "Method": "GetSaveQuestions",
    "RelativePath": "api/Save/GetSaveQuestions",
    "HttpMethod": "GET",
    "IsController": true,
    "Order": 0,
    "Parameters": [],
    "ReturnTypes": []
  },
  {
    "ContainingType": "ProjectAPI.Controllers.TestLevelController",
    "Method": "AddQuestionInTest",
    "RelativePath": "api/TestLevel/AddQuestionInTest",
    "HttpMethod": "POST",
    "IsController": true,
    "Order": 0,
    "Parameters": [
      {
        "Name": "dto",
        "Type": "ProjectAPI.DTO.AddQuestionInTestDTO",
        "IsRequired": true
      }
    ],
    "ReturnTypes": []
  },
  {
    "ContainingType": "ProjectAPI.Controllers.TestLevelController",
    "Method": "CompareAnswer",
    "RelativePath": "api/TestLevel/CompareAnswer/{questionId}/{selectedAnwser}",
    "HttpMethod": "POST",
    "IsController": true,
    "Order": 0,
    "Parameters": [
      {
        "Name": "questionId",
        "Type": "System.String",
        "IsRequired": true
      },
      {
        "Name": "selectedAnwser",
        "Type": "System.String",
        "IsRequired": true
      }
    ],
    "ReturnTypes": []
  },
  {
    "ContainingType": "ProjectAPI.Controllers.TestLevelController",
    "Method": "DeleteQuestionInTest",
    "RelativePath": "api/TestLevel/DeleteQuestionInTest/{questionId}",
    "HttpMethod": "DELETE",
    "IsController": true,
    "Order": 0,
    "Parameters": [
      {
        "Name": "questionId",
        "Type": "System.String",
        "IsRequired": true
      }
    ],
    "ReturnTypes": []
  },
  {
    "ContainingType": "ProjectAPI.Controllers.TestLevelController",
    "Method": "DetermineLevel",
    "RelativePath": "api/TestLevel/DetermineLevel",
    "HttpMethod": "GET",
    "IsController": true,
    "Order": 0,
    "Parameters": [
      {
        "Name": "count",
        "Type": "System.Int32",
        "IsRequired": false
      }
    ],
    "ReturnTypes": []
  },
  {
    "ContainingType": "ProjectAPI.Controllers.TestLevelController",
    "Method": "GetQuestionForTesting",
    "RelativePath": "api/TestLevel/QuestionForTesting/{framework}",
    "HttpMethod": "GET",
    "IsController": true,
    "Order": 0,
    "Parameters": [
      {
        "Name": "framework",
        "Type": "System.String",
        "IsRequired": true
      }
    ],
    "ReturnTypes": []
  },
  {
    "ContainingType": "ProjectAPI.Controllers.TestLevelController",
    "Method": "UpdateQuestionInTest",
    "RelativePath": "api/TestLevel/UpdateQuestionInTest/{questionId}",
    "HttpMethod": "PUT",
    "IsController": true,
    "Order": 0,
    "Parameters": [
      {
        "Name": "dto",
        "Type": "ProjectAPI.DTO.UpdateQuestionInTestDTO",
        "IsRequired": true
      },
      {
        "Name": "questionId",
        "Type": "System.String",
        "IsRequired": true
      }
    ],
    "ReturnTypes": []
  },
  {
    "ContainingType": "ProjectAPI.Controllers.UserGroupController",
    "Method": "GetAllUserGroups",
    "RelativePath": "api/UserGroup/GetAllUserGroups",
    "HttpMethod": "GET",
    "IsController": true,
    "Order": 0,
    "Parameters": [],
    "ReturnTypes": []
  },
  {
    "ContainingType": "ProjectAPI.Controllers.UserGroupController",
    "Method": "GetUserGroupById",
    "RelativePath": "api/UserGroup/GetUserGroupById/{id}",
    "HttpMethod": "GET",
    "IsController": true,
    "Order": 0,
    "Parameters": [
      {
        "Name": "id",
        "Type": "System.String",
        "IsRequired": true
      }
    ],
    "ReturnTypes": []
  },
  {
    "ContainingType": "ProjectAPI.Controllers.UserGroupController",
    "Method": "JoinGroup",
    "RelativePath": "api/UserGroup/JoinGroup",
    "HttpMethod": "POST",
    "IsController": true,
    "Order": 0,
    "Parameters": [
      {
        "Name": "dto",
        "Type": "ProjectAPI.DTO.GroupRequestDTO",
        "IsRequired": true
      }
    ],
    "ReturnTypes": []
  },
  {
    "ContainingType": "ProjectAPI.Controllers.UserGroupController",
    "Method": "LeaveGroup",
    "RelativePath": "api/UserGroup/LeaveGroup",
    "HttpMethod": "POST",
    "IsController": true,
    "Order": 0,
    "Parameters": [
      {
        "Name": "dto",
        "Type": "ProjectAPI.DTO.GroupRequestDTO",
        "IsRequired": true
      }
    ],
    "ReturnTypes": []
  }
]